{
  "indexes": [
    {
      "collectionGroup": "assets",
      "queryScope": "COLLECTION",
      "fields": [
        { "fieldPath": "parentPath", "order": "ASCENDING" },
        { "fieldPath": "kind", "order": "DESCENDING" },
        { "fieldPath": "name", "order": "ASCENDING" }
      ]
    },
    {
      "collectionGroup": "contents",
      "queryScope": "COLLECTION",
      "fields": [
        { "fieldPath": "parentSlug", "order": "ASCENDING" },
        { "fieldPath": "kind", "order": "DESCENDING" },
        { "fieldPath": "name", "order": "ASCENDING" }
      ]
    },
    {
      "collectionGroup": "schemas",
      "queryScope": "COLLECTION",
      "fields": [
        { "fieldPath": "type", "order": "ASCENDING" },
        { "fieldPath": "name", "order": "ASCENDING" }
      ]
    }
  ],
  "fieldOverrides": []
}
